passify/__init__.py
passify/passify.py
icinga_passify-0.1.dist-info/LICENSE
icinga_passify-0.1.dist-info/METADATA
icinga_passify-0.1.dist-info/WHEEL
icinga_passify-0.1.dist-info/entry_points.txt
icinga_passify-0.1.dist-info/top_level.txt
icinga_passify-0.1.dist-info/RECORD
