Metadata-Version: 2.1
Name: icinga-passify
Version: 0.1
Summary: An icinga check_command wrapper to icinga api for submitting passive check results.
Author-email: Bona Fide IT GmbH <github@bona-fide.it>, Olaf Rühenbeck <oruehenbeck@bona-fide.it>
License: MIT License
Project-URL: Homepage, https://github.com/BonaFideIT/passify
Keywords: icinga,api,passive,check_command
Classifier: License :: OSI Approved :: MIT License
Classifier: Programming Language :: Python
Classifier: Programming Language :: Python :: 3
Requires-Python: >=3.2
License-File: LICENSE
Provides-Extra: dev
Requires-Dist: pipenv; extra == "dev"
Requires-Dist: black; extra == "dev"
Requires-Dist: ruff; extra == "dev"
Requires-Dist: pre-commit; extra == "dev"
